merges3logs.py
merges3logs-1.0.1.dist-info/METADATA
merges3logs-1.0.1.dist-info/WHEEL
merges3logs-1.0.1.dist-info/entry_points.txt
merges3logs-1.0.1.dist-info/licenses/LICENSE
merges3logs-1.0.1.dist-info/RECORD
