Metadata-Version: 2.1
Name: merges3logs
Version: 1.0.1
Summary: Download cloudfront logs from S3 and merge them into a single log file for the day.
Project-URL: Source, https://github.com/linsomniac/merges3logs
Author-email: Sean Reifschneider <jafo00@gmail.com>
Maintainer-email: Sean Reifschneider <jafo00@gmail.com>
License: Creative Commons Legal Code
License-File: LICENSE
Keywords: aws,logfile,s3
Classifier: Development Status :: 4 - Beta
Classifier: License :: CC0 1.0 Universal (CC0 1.0) Public Domain Dedication
Classifier: Natural Language :: English
Requires-Python: >=3.8
Requires-Dist: boto3
Requires-Dist: click
Provides-Extra: lint
Requires-Dist: black; extra == 'lint'
Requires-Dist: mypy; extra == 'lint'
Requires-Dist: ruff; extra == 'lint'
Provides-Extra: test
Requires-Dist: pytest; extra == 'test'
